{"cameraMode":{"drawMode":0,"name":"Shaded","section":"Shading Mode"},"sceneLighting":true,"audioPlay":false,"sceneViewState":{"m_AlwaysRefresh":false,"showFog":true,"showSkybox":true,"showFlares":true,"showImageEffects":true,"showParticleSystems":true,"showVisualEffectGraphs":true,"m_FxEnabled":true},"in2DMode":false,"pivot":{"x":9.250320434570313,"y":1.5427302122116089,"z":13.269013404846192},"rotation":{"x":0.14390349388122559,"y":0.4457226097583771,"z":-0.07284495234489441,"w":0.8805111646652222},"size":2.003941535949707,"orthographic":false}